OSMerge-0.0.0.dist-info/DESCRIPTION.rst
OSMerge-0.0.0.dist-info/METADATA
OSMerge-0.0.0.dist-info/RECORD
OSMerge-0.0.0.dist-info/WHEEL
OSMerge-0.0.0.dist-info/entry_points.txt
OSMerge-0.0.0.dist-info/metadata.json
OSMerge-0.0.0.dist-info/top_level.txt
osmerge/__init__.py
osmerge/__main__.py
osmerge/cli.py
osmerge/utils.py
osmerge/tests/__init__.py
osmerge/tests/conftest.py
osmerge/tests/test_utils.py
site/__init__.py
tests/__init__.py
tests/conftest.py
tests/test_cli.py
