Metadata-Version: 2.0
Name: OSMerge
Version: 0.0.0
Summary: Merges custom data sets with OpenStreetMap polygons.
Home-page: https://github.com/citizenlabsgr/osmerge
Author: Citizen Labs
Author-email: info@citizenlabs.org
License: MIT
Platform: UNKNOWN
Classifier: Development Status :: 1 - Planning
Classifier: Natural Language :: English
Classifier: Operating System :: OS Independent
Classifier: Programming Language :: Python
Classifier: Programming Language :: Python :: 2
Classifier: Programming Language :: Python :: 2.7
Classifier: Programming Language :: Python :: 3
Classifier: Programming Language :: Python :: 3.3
Classifier: Programming Language :: Python :: 3.4
Classifier: Programming Language :: Python :: 3.5
Requires-Dist: click (==6.6)
Requires-Dist: osmapi (==0.4.1)
Requires-Dist: shapely (==1.5.2)
